Workbook

Sheet Paramètres
A1: PARAMÈTRES ET LISTES DE CONTRÔLE
A2: Fichier de suivi numérique – Ebrié Lagoon Experience | Version de travail pour exploitation, contrôle interne et reporting bancaire
A4: Paramètre | B4: Valeur
A5: Nom du projet | B5: Ebrié Lagoon Experience
A6: Promoteur | B6: SARR Macoumba
A7: Localisation | B7: Abidjan – Lagune Ébrié
A8: Date de démarrage suivi | B8: 46174
A9: Taux satisfaction cible | B9: 0.85
A10: Taux ponctualité cible | B10: 0.9
A11: Seuil alerte incidents graves | B11: 0
A13: Listes déroulantes | B13: Statuts | C13: Prestations | D13: Modes paiement | E13: Niveaux météo | F13: Niveaux incident | G13: Canaux | H13: Oui/Non
B14: En attente | C14: Balade simple | D14: Espèces | E14: Vert | F14: Mineur | G14: WhatsApp | H14: Oui
B15: Confirmée | C15: Sunset Experience | D15: Mobile Money | E15: Orange | F15: Significatif | G15: Téléphone | H15: Non
B16: Réalisée | C16: Anniversaire | D16: Virement | E16: Rouge | F16: Grave | G16: Instagram
B17: Reportée | C17: Demande en mariage | D17: Carte/Terminal | G17: Facebook
B18: Annulée | C18: VIP / Premium | G18: Partenaire
B19: Clôturée | C19: Corporate | G19: Recommandation
A21: Source documentaire | B21: Manuel d’exploitation et procédures – Ebrié Lagoon Experience, version améliorée, juin 2026

Sheet Réservations
A1: REGISTRE NUMÉRIQUE DES RÉSERVATIONS CLIENTS
A2: Fichier de suivi numérique – Ebrié Lagoon Experience | Version de travail pour exploitation, contrôle interne et reporting bancaire
A4: N° réservation | B4: Date demande | C4: Canal | D4: Nom client | E4: Téléphone/WhatsApp | F4: Email | G4: Type prestation | H4: Date prestation | I4: Heure | J4: Nb participants | K4: Options demandées | L4: Montant convenu (FCFA) | M4: Acompte payé (FCFA) | N4: Solde restant (FCFA) | O4: Mode paiement | P4: Bateau / partenaire | Q4: Statut | R4: Observations
A5: RES-0001 | N5: =IF(L5="","",L5-M5)
A6: RES-0002 | N6: =IF(L6="","",L6-M6)
A7: RES-0003 | N7: =IF(L7="","",L7-M7)
A8: RES-0004 | N8: =IF(L8="","",L8-M8)
A9: RES-0005 | N9: =IF(L9="","",L9-M9)
A10: RES-0006 | N10: =IF(L10="","",L10-M10)
A11: RES-0007 | N11: =IF(L11="","",L11-M11)
A12: RES-0008 | N12: =IF(L12="","",L12-M12)
A13: RES-0009 | N13: =IF(L13="","",L13-M13)
A14: RES-0010 | N14: =IF(L14="","",L14-M14)
A15: RES-0011 | N15: =IF(L15="","",L15-M15)
A16: RES-0012 | N16: =IF(L16="","",L16-M16)
... A104: RES-0100 | N104: =IF(L104="","",L104-M104)

Sheet Contrôle bateau
A1: FICHE NUMÉRIQUE DE CONTRÔLE BATEAU AVANT DÉPART
A2: Fichier de suivi numérique – Ebrié Lagoon Experience | Version de travail pour exploitation, contrôle interne et reporting bancaire
A4: N° contrôle | B4: Date sortie | C4: N° réservation | D4: Bateau identifié | E4: Partenaire nautique | F4: Pilote présent | G4: Pilote qualifié | H4: Assurance valide | I4: Capacité max | J4: Passagers prévus | K4: Gilets suffisants | L4: Bouée disponible | M4: Trousse secours | N4: Moyen communication | O4: Météo | P4: Départ autorisé | Q4: Observations
A5: CTRL-0001
A6: CTRL-0002
A7: CTRL-0003
A8: CTRL-0004
A9: CTRL-0005
A10: CTRL-0006
A11: CTRL-0007
A12: CTRL-0008
A13: CTRL-0009
A14: CTRL-0010
A15: CTRL-0011
A16: CTRL-0012
... A104: CTRL-0100

Sheet Incidents
A1: REGISTRE DES INCIDENTS, URGENCES ET SINISTRES
A2: Fichier de suivi numérique – Ebrié Lagoon Experience | Version de travail pour exploitation, contrôle interne et reporting bancaire
A4: N° incident | B4: Date/heure | C4: N° réservation | D4: Lieu | E4: Prestation concernée | F4: Client/personnes concernées | G4: Nature incident | H4: Niveau | I4: Mesures immédiates | J4: Secours/autorités contactés | K4: Assureur informé | L4: Date déclaration assureur | M4: Responsable suivi | N4: Action corrective | O4: Statut | P4: Coût estimé (FCFA) | Q4: Remboursement assurance (FCFA) | R4: Impact net (FCFA) | S4: Observations
A5: INC-0001 | R5: =IF(P5="","",P5-Q5)
A6: INC-0002 | R6: =IF(P6="","",P6-Q6)
A7: INC-0003 | R7: =IF(P7="","",P7-Q7)
A8: INC-0004 | R8: =IF(P8="","",P8-Q8)
A9: INC-0005 | R9: =IF(P9="","",P9-Q9)
A10: INC-0006 | R10: =IF(P10="","",P10-Q10)
A11: INC-0007 | R11: =IF(P11="","",P11-Q11)
A12: INC-0008 | R12: =IF(P12="","",P12-Q12)
A13: INC-0009 | R13: =IF(P13="","",P13-Q13)
A14: INC-0010 | R14: =IF(P14="","",P14-Q14)
A15: INC-0011 | R15: =IF(P15="","",P15-Q15)
A16: INC-0012 | R16: =IF(P16="","",P16-Q16)
... A104: INC-0100 | R104: =IF(P104="","",P104-Q104)

Sheet Réclamations
A1: REGISTRE DES RÉCLAMATIONS CLIENTS
A2: Fichier de suivi numérique – Ebrié Lagoon Experience | Version de travail pour exploitation, contrôle interne et reporting bancaire
A4: N° réclamation | B4: Date réception | C4: N° réservation | D4: Nom client | E4: Date prestation | F4: Objet réclamation | G4: Description | H4: Pièces reçues | I4: Analyse interne | J4: Réponse proposée | K4: Date réponse | L4: Délai traitement (jours) | M4: Statut | N4: Action corrective | O4: Responsable | P4: Observations
A5: REC-0001 | L5: =IF(K5="","",K5-B5)
A6: REC-0002 | L6: =IF(K6="","",K6-B6)
A7: REC-0003 | L7: =IF(K7="","",K7-B7)
A8: REC-0004 | L8: =IF(K8="","",K8-B8)
A9: REC-0005 | L9: =IF(K9="","",K9-B9)
A10: REC-0006 | L10: =IF(K10="","",K10-B10)
A11: REC-0007 | L11: =IF(K11="","",K11-B11)
A12: REC-0008 | L12: =IF(K12="","",K12-B12)
A13: REC-0009 | L13: =IF(K13="","",K13-B13)
A14: REC-0010 | L14: =IF(K14="","",K14-B14)
A15: REC-0011 | L15: =IF(K15="","",K15-B15)
A16: REC-0012 | L16: =IF(K16="","",K16-B16)
... A104: REC-0100 | L104: =IF(K104="","",K104-B104)

Sheet Paiements
A1: REGISTRE DES PAIEMENTS, ENCAISSEMENTS ET RÈGLEMENTS PARTENAIRES
A2: Fichier de suivi numérique – Ebrié Lagoon Experience | Version de travail pour exploitation, contrôle interne et reporting bancaire
A4: N° mouvement | B4: Date | C4: Type flux | D4: N° réservation | E4: Partenaire / Client | F4: Objet | G4: Mode paiement | H4: Référence paiement | I4: Montant entrée (FCFA) | J4: Montant sortie (FCFA) | K4: Solde net (FCFA) | L4: Justificatif disponible | M4: Validation interne | N4: Responsable | O4: Rapproché banque | P4: Date rapprochement | Q4: Observations
A5: MVT-0001 | K5: =IF(AND(I5="",J5=""),"",I5-J5)
A6: MVT-0002 | K6: =IF(AND(I6="",J6=""),"",I6-J6)
A7: MVT-0003 | K7: =IF(AND(I7="",J7=""),"",I7-J7)
A8: MVT-0004 | K8: =IF(AND(I8="",J8=""),"",I8-J8)
A9: MVT-0005 | K9: =IF(AND(I9="",J9=""),"",I9-J9)
A10: MVT-0006 | K10: =IF(AND(I10="",J10=""),"",I10-J10)
A11: MVT-0007 | K11: =IF(AND(I11="",J11=""),"",I11-J11)
A12: MVT-0008 | K12: =IF(AND(I12="",J12=""),"",I12-J12)
A13: MVT-0009 | K13: =IF(AND(I13="",J13=""),"",I13-J13)
A14: MVT-0010 | K14: =IF(AND(I14="",J14=""),"",I14-J14)
A15: MVT-0011 | K15: =IF(AND(I15="",J15=""),"",I15-J15)
A16: MVT-0012 | K16: =IF(AND(I16="",J16=""),"",I16-J16)
... A204: MVT-0200 | K204: =IF(AND(I204="",J204=""),"",I204-J204)

Sheet Partenaires
A1: REGISTRE DES PARTENAIRES NAUTIQUES, TRAITEURS ET PRESTATAIRES
A2: Fichier de suivi numérique – Ebrié Lagoon Experience | Version de travail pour exploitation, contrôle interne et reporting bancaire
A4: Code partenaire | B4: Type partenaire | C4: Nom / Raison sociale | D4: Contact | E4: Email | F4: RCCM / Identifiant | G4: Document fourni | H4: Assurance / conformité | I4: Date signature convention | J4: Date expiration | K4: Tarif convenu | L4: Disponibilité prioritaire | M4: Statut | N4: Dernière évaluation | O4: Note qualité /5 | P4: Incidents liés | Q4: Observations
A5: PAR-0001
A6: PAR-0002
A7: PAR-0003
A8: PAR-0004
A9: PAR-0005
A10: PAR-0006
A11: PAR-0007
A12: PAR-0008
A13: PAR-0009
A14: PAR-0010
A15: PAR-0011
A16: PAR-0012
... A104: PAR-0100

Sheet Assurances
A1: REGISTRE DES ASSURANCES ET SINISTRES DÉCLARÉS
A2: Fichier de suivi numérique – Ebrié Lagoon Experience | Version de travail pour exploitation, contrôle interne et reporting bancaire
A4: N° police | B4: Assureur | C4: Type couverture | D4: Objet couvert | E4: Capital assuré (FCFA) | F4: Prime annuelle (FCFA) | G4: Date effet | H4: Date expiration | I4: Statut | J4: Attestation disponible | K4: Contact assureur | L4: Sinistre lié | M4: Date déclaration | N4: Montant déclaré | O4: Montant indemnisé | P4: Reste à charge | Q4: Observations
A5: POL-001 | C5: RC Professionnelle | D5: Responsabilité civile exploitation / tiers / clients | E5: 50000000 | I5: À souscrire | P5: =IF(N5="","",N5-O5)
A6: POL-002 | C6: Assurance Passagers | D6: Décès accidentel, invalidité, frais médicaux, assistance | E6: 50000000 | I6: À souscrire | P6: =IF(N6="","",N6-O6)
A7: POL-003 | C7: Assurance Événementielle | D7: Annulation, interruption, responsabilité événementielle | I7: À souscrire | P7: =IF(N7="","",N7-O7)
A8: POL-004 | C8: Assurance Matériel | D8: Équipements professionnels, événementiels, digitaux | E8: 12000000 | I8: À souscrire | P8: =IF(N8="","",N8-O8)
A9: POL-005 | C9: Cyber-risque | D9: Données clients et outils numériques | I9: Optionnelle | P9: =IF(N9="","",N9-O9)
A10: POL-006 | P10: =IF(N10="","",N10-O10)
A11: POL-007 | P11: =IF(N11="","",N11-O11)
A12: POL-008 | P12: =IF(N12="","",N12-O12)
A13: POL-009 | P13: =IF(N13="","",N13-O13)
A14: POL-010 | P14: =IF(N14="","",N14-O14)
A15: POL-011 | P15: =IF(N15="","",N15-O15)
A16: POL-012 | P16: =IF(N16="","",N16-O16)
A17: POL-013 | P17: =IF(N17="","",N17-O17)
A18: POL-014 | P18: =IF(N18="","",N18-O18)
A19: POL-015 | P19: =IF(N19="","",N19-O19)
A20: POL-016 | P20: =IF(N20="","",N20-O20)
A21: POL-017 | P21: =IF(N21="","",N21-O21)
... A54: POL-050 | P54: =IF(N54="","",N54-O54)

Sheet Tableau de bord
A1: TABLEAU DE BORD MENSUEL – EXPLOITATION ET REPORTING BANCAIRE
A2: Fichier de suivi numérique – Ebrié Lagoon Experience | Version de travail pour exploitation, contrôle interne et reporting bancaire
A4: Indicateur | B4: Janv. | C4: Févr. | D4: Mars | E4: Avr. | F4: Mai | G4: Juin | H4: Juil. | I4: Août | J4: Sept. | K4: Oct. | L4: Nov. | M4: Déc. | N4: Total / Moyenne
A5: Nombre de réservations | B5: =COUNTIFS(Réservations!$H:$H,">="&DATE(YEAR(Paramètres!$B$7),1,1),Réservations!$H:$H,"<"&EDATE(DATE(YEAR(Paramètres!$B$7),1,1),1)) -> 0 | C5: =COUNTIFS(Réservations!$H:$H,">="&DATE(YEAR(Paramètres!$B$7),2,1),Réservations!$H:$H,"<"&EDATE(DATE(YEAR(Paramètres!$B$7),2,1),1)) -> 0 | D5: =COUNTIFS(Réservations!$H:$H,">="&DATE(YEAR(Paramètres!$B$7),3,1),Réservations!$H:$H,"<"&EDATE(DATE(YEAR(Paramètres!$B$7),3,1),1)) -> 0 | E5: =COUNTIFS(Réservations!$H:$H,">="&DATE(YEAR(Paramètres!$B$7),4,1),Réservations!$H:$H,"<"&EDATE(DATE(YEAR(Paramètres!$B$7),4,1),1)) -> 0 | F5: =COUNTIFS(Réservations!$H:$H,">="&DATE(YEAR(Paramètres!$B$7),5,1),Réservations!$H:$H,"<"&EDATE(DATE(YEAR(Paramètres!$B$7),5,1),1)) -> 0 | G5: =COUNTIFS(Réservations!$H:$H,">="&DATE(YEAR(Paramètres!$B$7),6,1),Réservations!$H:$H,"<"&EDATE(DATE(YEAR(Paramètres!$B$7),6,1),1)) -> 0 | H5: =COUNTIFS(Réservations!$H:$H,">="&DATE(YEAR(Paramètres!$B$7),7,1),Réservations!$H:$H,"<"&EDATE(DATE(YEAR(Paramètres!$B$7),7,1),1)) -> 0 | I5: =COUNTIFS(Réservations!$H:$H,">="&DATE(YEAR(Paramètres!$B$7),8,1),Réservations!$H:$H,"<"&EDATE(DATE(YEAR(Paramètres!$B$7),8,1),1)) -> 0 | J5: =COUNTIFS(Réservations!$H:$H,">="&DATE(YEAR(Paramètres!$B$7),9,1),Réservations!$H:$H,"<"&EDATE(DATE(YEAR(Paramètres!$B$7),9,1),1)) -> 0 | K5: =COUNTIFS(Réservations!$H:$H,">="&DATE(YEAR(Paramètres!$B$7),10,1),Réservations!$H:$H,"<"&EDATE(DATE(YEAR(Paramètres!$B$7),10,1),1)) -> 0 | L5: =COUNTIFS(Réservations!$H:$H,">="&DATE(YEAR(Paramètres!$B$7),11,1),Réservations!$H:$H,"<"&EDATE(DATE(YEAR(Paramètres!$B$7),11,1),1)) -> 0 | M5: =COUNTIFS(Réservations!$H:$H,">="&DATE(YEAR(Paramètres!$B$7),12,1),Réservations!$H:$H,"<"&EDATE(DATE(YEAR(Paramètres!$B$7),12,1),1)) -> 0 | N5: =SUM(B5:M5) -> 0
A6: Nombre de sorties réalisées | B6: =COUNTIFS(Réservations!$H:$H,">="&DATE(YEAR(Paramètres!$B$7),1,1),Réservations!$H:$H,"<"&EDATE(DATE(YEAR(Paramètres!$B$7),1,1),1),Réservations!$Q:$Q,"Réalisée") -> 0 | C6: =COUNTIFS(Réservations!$H:$H,">="&DATE(YEAR(Paramètres!$B$7),2,1),Réservations!$H:$H,"<"&EDATE(DATE(YEAR(Paramètres!$B$7),2,1),1),Réservations!$Q:$Q,"Réalisée") -> 0 | D6: =COUNTIFS(Réservations!$H:$H,">="&DATE(YEAR(Paramètres!$B$7),3,1),Réservations!$H:$H,"<"&EDATE(DATE(YEAR(Paramètres!$B$7),3,1),1),Réservations!$Q:$Q,"Réalisée") -> 0 | E6: =COUNTIFS(Réservations!$H:$H,">="&DATE(YEAR(Paramètres!$B$7),4,1),Réservations!$H:$H,"<"&EDATE(DATE(YEAR(Paramètres!$B$7),4,1),1),Réservations!$Q:$Q,"Réalisée") -> 0 | F6: =COUNTIFS(Réservations!$H:$H,">="&DATE(YEAR(Paramètres!$B$7),5,1),Réservations!$H:$H,"<"&EDATE(DATE(YEAR(Paramètres!$B$7),5,1),1),Réservations!$Q:$Q,"Réalisée") -> 0 | G6: =COUNTIFS(Réservations!$H:$H,">="&DATE(YEAR(Paramètres!$B$7),6,1),Réservations!$H:$H,"<"&EDATE(DATE(YEAR(Paramètres!$B$7),6,1),1),Réservations!$Q:$Q,"Réalisée") -> 0 | H6: =COUNTIFS(Réservations!$H:$H,">="&DATE(YEAR(Paramètres!$B$7),7,1),Réservations!$H:$H,"<"&EDATE(DATE(YEAR(Paramètres!$B$7),7,1),1),Réservations!$Q:$Q,"Réalisée") -> 0 | I6: =COUNTIFS(Réservations!$H:$H,">="&DATE(YEAR(Paramètres!$B$7),8,1),Réservations!$H:$H,"<"&EDATE(DATE(YEAR(Paramètres!$B$7),8,1),1),Réservations!$Q:$Q,"Réalisée") -> 0 | J6: =COUNTIFS(Réservations!$H:$H,">="&DATE(YEAR(Paramètres!$B$7),9,1),Réservations!$H:$H,"<"&EDATE(DATE(YEAR(Paramètres!$B$7),9,1),1),Réservations!$Q:$Q,"Réalisée") -> 0 | K6: =COUNTIFS(Réservations!$H:$H,">="&DATE(YEAR(Paramètres!$B$7),10,1),Réservations!$H:$H,"<"&EDATE(DATE(YEAR(Paramètres!$B$7),10,1),1),Réservations!$Q:$Q,"Réalisée") -> 0 | L6: =COUNTIFS(Réservations!$H:$H,">="&DATE(YEAR(Paramètres!$B$7),11,1),Réservations!$H:$H,"<"&EDATE(DATE(YEAR(Paramètres!$B$7),11,1),1),Réservations!$Q:$Q,"Réalisée") -> 0 | M6: =COUNTIFS(Réservations!$H:$H,">="&DATE(YEAR(Paramètres!$B$7),12,1),Réservations!$H:$H,"<"&EDATE(DATE(YEAR(Paramètres!$B$7),12,1),1),Réservations!$Q:$Q,"Réalisée") -> 0 | N6: =SUM(B6:M6) -> 0
A7: Chiffre d’affaires encaissé (FCFA) | B7: =SUMIFS(Paiements!$I:$I,Paiements!$B:$B,">="&DATE(YEAR(Paramètres!$B$7),1,1),Paiements!$B:$B,"<"&EDATE(DATE(YEAR(Paramètres!$B$7),1,1),1)) -> 0 | C7: =SUMIFS(Paiements!$I:$I,Paiements!$B:$B,">="&DATE(YEAR(Paramètres!$B$7),2,1),Paiements!$B:$B,"<"&EDATE(DATE(YEAR(Paramètres!$B$7),2,1),1)) -> 0 | D7: =SUMIFS(Paiements!$I:$I,Paiements!$B:$B,">="&DATE(YEAR(Paramètres!$B$7),3,1),Paiements!$B:$B,"<"&EDATE(DATE(YEAR(Paramètres!$B$7),3,1),1)) -> 0 | E7: =SUMIFS(Paiements!$I:$I,Paiements!$B:$B,">="&DATE(YEAR(Paramètres!$B$7),4,1),Paiements!$B:$B,"<"&EDATE(DATE(YEAR(Paramètres!$B$7),4,1),1)) -> 0 | F7: =SUMIFS(Paiements!$I:$I,Paiements!$B:$B,">="&DATE(YEAR(Paramètres!$B$7),5,1),Paiements!$B:$B,"<"&EDATE(DATE(YEAR(Paramètres!$B$7),5,1),1)) -> 0 | G7: =SUMIFS(Paiements!$I:$I,Paiements!$B:$B,">="&DATE(YEAR(Paramètres!$B$7),6,1),Paiements!$B:$B,"<"&EDATE(DATE(YEAR(Paramètres!$B$7),6,1),1)) -> 0 | H7: =SUMIFS(Paiements!$I:$I,Paiements!$B:$B,">="&DATE(YEAR(Paramètres!$B$7),7,1),Paiements!$B:$B,"<"&EDATE(DATE(YEAR(Paramètres!$B$7),7,1),1)) -> 0 | I7: =SUMIFS(Paiements!$I:$I,Paiements!$B:$B,">="&DATE(YEAR(Paramètres!$B$7),8,1),Paiements!$B:$B,"<"&EDATE(DATE(YEAR(Paramètres!$B$7),8,1),1)) -> 0 | J7: =SUMIFS(Paiements!$I:$I,Paiements!$B:$B,">="&DATE(YEAR(Paramètres!$B$7),9,1),Paiements!$B:$B,"<"&EDATE(DATE(YEAR(Paramètres!$B$7),9,1),1)) -> 0 | K7: =SUMIFS(Paiements!$I:$I,Paiements!$B:$B,">="&DATE(YEAR(Paramètres!$B$7),10,1),Paiements!$B:$B,"<"&EDATE(DATE(YEAR(Paramètres!$B$7),10,1),1)) -> 0 | L7: =SUMIFS(Paiements!$I:$I,Paiements!$B:$B,">="&DATE(YEAR(Paramètres!$B$7),11,1),Paiements!$B:$B,"<"&EDATE(DATE(YEAR(Paramètres!$B$7),11,1),1)) -> 0 | M7: =SUMIFS(Paiements!$I:$I,Paiements!$B:$B,">="&DATE(YEAR(Paramètres!$B$7),12,1),Paiements!$B:$B,"<"&EDATE(DATE(YEAR(Paramètres!$B$7),12,1),1)) -> 0 | N7: =SUM(B7:M7) -> 0
A8: Dépenses payées (FCFA) | B8: =SUMIFS(Paiements!$J:$J,Paiements!$B:$B,">="&DATE(YEAR(Paramètres!$B$7),1,1),Paiements!$B:$B,"<"&EDATE(DATE(YEAR(Paramètres!$B$7),1,1),1)) -> 0 | C8: =SUMIFS(Paiements!$J:$J,Paiements!$B:$B,">="&DATE(YEAR(Paramètres!$B$7),2,1),Paiements!$B:$B,"<"&EDATE(DATE(YEAR(Paramètres!$B$7),2,1),1)) -> 0 | D8: =SUMIFS(Paiements!$J:$J,Paiements!$B:$B,">="&DATE(YEAR(Paramètres!$B$7),3,1),Paiements!$B:$B,"<"&EDATE(DATE(YEAR(Paramètres!$B$7),3,1),1)) -> 0 | E8: =SUMIFS(Paiements!$J:$J,Paiements!$B:$B,">="&DATE(YEAR(Paramètres!$B$7),4,1),Paiements!$B:$B,"<"&EDATE(DATE(YEAR(Paramètres!$B$7),4,1),1)) -> 0 | F8: =SUMIFS(Paiements!$J:$J,Paiements!$B:$B,">="&DATE(YEAR(Paramètres!$B$7),5,1),Paiements!$B:$B,"<"&EDATE(DATE(YEAR(Paramètres!$B$7),5,1),1)) -> 0 | G8: =SUMIFS(Paiements!$J:$J,Paiements!$B:$B,">="&DATE(YEAR(Paramètres!$B$7),6,1),Paiements!$B:$B,"<"&EDATE(DATE(YEAR(Paramètres!$B$7),6,1),1)) -> 0 | H8: =SUMIFS(Paiements!$J:$J,Paiements!$B:$B,">="&DATE(YEAR(Paramètres!$B$7),7,1),Paiements!$B:$B,"<"&EDATE(DATE(YEAR(Paramètres!$B$7),7,1),1)) -> 0 | I8: =SUMIFS(Paiements!$J:$J,Paiements!$B:$B,">="&DATE(YEAR(Paramètres!$B$7),8,1),Paiements!$B:$B,"<"&EDATE(DATE(YEAR(Paramètres!$B$7),8,1),1)) -> 0 | J8: =SUMIFS(Paiements!$J:$J,Paiements!$B:$B,">="&DATE(YEAR(Paramètres!$B$7),9,1),Paiements!$B:$B,"<"&EDATE(DATE(YEAR(Paramètres!$B$7),9,1),1)) -> 0 | K8: =SUMIFS(Paiements!$J:$J,Paiements!$B:$B,">="&DATE(YEAR(Paramètres!$B$7),10,1),Paiements!$B:$B,"<"&EDATE(DATE(YEAR(Paramètres!$B$7),10,1),1)) -> 0 | L8: =SUMIFS(Paiements!$J:$J,Paiements!$B:$B,">="&DATE(YEAR(Paramètres!$B$7),11,1),Paiements!$B:$B,"<"&EDATE(DATE(YEAR(Paramètres!$B$7),11,1),1)) -> 0 | M8: =SUMIFS(Paiements!$J:$J,Paiements!$B:$B,">="&DATE(YEAR(Paramètres!$B$7),12,1),Paiements!$B:$B,"<"&EDATE(DATE(YEAR(Paramètres!$B$7),12,1),1)) -> 0 | N8: =SUM(B8:M8) -> 0
A9: Solde net de trésorerie (FCFA) | B9: =B7-B8 -> 0 | C9: =C7-C8 -> 0 | D9: =D7-D8 -> 0 | E9: =E7-E8 -> 0 | F9: =F7-F8 -> 0 | G9: =G7-G8 -> 0 | H9: =H7-H8 -> 0 | I9: =I7-I8 -> 0 | ... M9: =M7-M8 -> 0 | N9: =SUM(B9:M9) -> 0
A10: Réclamations reçues | B10: =COUNTIFS(Réclamations!$B:$B,">="&DATE(YEAR(Paramètres!$B$7),1,1),Réclamations!$B:$B,"<"&EDATE(DATE(YEAR(Paramètres!$B$7),1,1),1)) -> 0 | C10: =COUNTIFS(Réclamations!$B:$B,">="&DATE(YEAR(Paramètres!$B$7),2,1),Réclamations!$B:$B,"<"&EDATE(DATE(YEAR(Paramètres!$B$7),2,1),1)) -> 0 | D10: =COUNTIFS(Réclamations!$B:$B,">="&DATE(YEAR(Paramètres!$B$7),3,1),Réclamations!$B:$B,"<"&EDATE(DATE(YEAR(Paramètres!$B$7),3,1),1)) -> 0 | E10: =COUNTIFS(Réclamations!$B:$B,">="&DATE(YEAR(Paramètres!$B$7),4,1),Réclamations!$B:$B,"<"&EDATE(DATE(YEAR(Paramètres!$B$7),4,1),1)) -> 0 | F10: =COUNTIFS(Réclamations!$B:$B,">="&DATE(YEAR(Paramètres!$B$7),5,1),Réclamations!$B:$B,"<"&EDATE(DATE(YEAR(Paramètres!$B$7),5,1),1)) -> 0 | G10: =COUNTIFS(Réclamations!$B:$B,">="&DATE(YEAR(Paramètres!$B$7),6,1),Réclamations!$B:$B,"<"&EDATE(DATE(YEAR(Paramètres!$B$7),6,1),1)) -> 0 | H10: =COUNTIFS(Réclamations!$B:$B,">="&DATE(YEAR(Paramètres!$B$7),7,1),Réclamations!$B:$B,"<"&EDATE(DATE(YEAR(Paramètres!$B$7),7,1),1)) -> 0 | I10: =COUNTIFS(Réclamations!$B:$B,">="&DATE(YEAR(Paramètres!$B$7),8,1),Réclamations!$B:$B,"<"&EDATE(DATE(YEAR(Paramètres!$B$7),8,1),1)) -> 0 | J10: =COUNTIFS(Réclamations!$B:$B,">="&DATE(YEAR(Paramètres!$B$7),9,1),Réclamations!$B:$B,"<"&EDATE(DATE(YEAR(Paramètres!$B$7),9,1),1)) -> 0 | K10: =COUNTIFS(Réclamations!$B:$B,">="&DATE(YEAR(Paramètres!$B$7),10,1),Réclamations!$B:$B,"<"&EDATE(DATE(YEAR(Paramètres!$B$7),10,1),1)) -> 0 | L10: =COUNTIFS(Réclamations!$B:$B,">="&DATE(YEAR(Paramètres!$B$7),11,1),Réclamations!$B:$B,"<"&EDATE(DATE(YEAR(Paramètres!$B$7),11,1),1)) -> 0 | M10: =COUNTIFS(Réclamations!$B:$B,">="&DATE(YEAR(Paramètres!$B$7),12,1),Réclamations!$B:$B,"<"&EDATE(DATE(YEAR(Paramètres!$B$7),12,1),1)) -> 0 | N10: =SUM(B10:M10) -> 0
A11: Réclamations clôturées | B11: =COUNTIFS(Réclamations!$B:$B,">="&DATE(YEAR(Paramètres!$B$7),1,1),Réclamations!$B:$B,"<"&EDATE(DATE(YEAR(Paramètres!$B$7),1,1),1),Réclamations!$M:$M,"Clôturée") -> 0 | C11: =COUNTIFS(Réclamations!$B:$B,">="&DATE(YEAR(Paramètres!$B$7),2,1),Réclamations!$B:$B,"<"&EDATE(DATE(YEAR(Paramètres!$B$7),2,1),1),Réclamations!$M:$M,"Clôturée") -> 0 | D11: =COUNTIFS(Réclamations!$B:$B,">="&DATE(YEAR(Paramètres!$B$7),3,1),Réclamations!$B:$B,"<"&EDATE(DATE(YEAR(Paramètres!$B$7),3,1),1),Réclamations!$M:$M,"Clôturée") -> 0 | E11: =COUNTIFS(Réclamations!$B:$B,">="&DATE(YEAR(Paramètres!$B$7),4,1),Réclamations!$B:$B,"<"&EDATE(DATE(YEAR(Paramètres!$B$7),4,1),1),Réclamations!$M:$M,"Clôturée") -> 0 | F11: =COUNTIFS(Réclamations!$B:$B,">="&DATE(YEAR(Paramètres!$B$7),5,1),Réclamations!$B:$B,"<"&EDATE(DATE(YEAR(Paramètres!$B$7),5,1),1),Réclamations!$M:$M,"Clôturée") -> 0 | G11: =COUNTIFS(Réclamations!$B:$B,">="&DATE(YEAR(Paramètres!$B$7),6,1),Réclamations!$B:$B,"<"&EDATE(DATE(YEAR(Paramètres!$B$7),6,1),1),Réclamations!$M:$M,"Clôturée") -> 0 | H11: =COUNTIFS(Réclamations!$B:$B,">="&DATE(YEAR(Paramètres!$B$7),7,1),Réclamations!$B:$B,"<"&EDATE(DATE(YEAR(Paramètres!$B$7),7,1),1),Réclamations!$M:$M,"Clôturée") -> 0 | I11: =COUNTIFS(Réclamations!$B:$B,">="&DATE(YEAR(Paramètres!$B$7),8,1),Réclamations!$B:$B,"<"&EDATE(DATE(YEAR(Paramètres!$B$7),8,1),1),Réclamations!$M:$M,"Clôturée") -> 0 | J11: =COUNTIFS(Réclamations!$B:$B,">="&DATE(YEAR(Paramètres!$B$7),9,1),Réclamations!$B:$B,"<"&EDATE(DATE(YEAR(Paramètres!$B$7),9,1),1),Réclamations!$M:$M,"Clôturée") -> 0 | K11: =COUNTIFS(Réclamations!$B:$B,">="&DATE(YEAR(Paramètres!$B$7),10,1),Réclamations!$B:$B,"<"&EDATE(DATE(YEAR(Paramètres!$B$7),10,1),1),Réclamations!$M:$M,"Clôturée") -> 0 | L11: =COUNTIFS(Réclamations!$B:$B,">="&DATE(YEAR(Paramètres!$B$7),11,1),Réclamations!$B:$B,"<"&EDATE(DATE(YEAR(Paramètres!$B$7),11,1),1),Réclamations!$M:$M,"Clôturée") -> 0 | M11: =COUNTIFS(Réclamations!$B:$B,">="&DATE(YEAR(Paramètres!$B$7),12,1),Réclamations!$B:$B,"<"&EDATE(DATE(YEAR(Paramètres!$B$7),12,1),1),Réclamations!$M:$M,"Clôturée") -> 0 | N11: =SUM(B11:M11) -> 0
A12: Incidents mineurs | B12: =COUNTIFS(Incidents!$B:$B,">="&DATE(YEAR(Paramètres!$B$7),1,1),Incidents!$B:$B,"<"&EDATE(DATE(YEAR(Paramètres!$B$7),1,1),1),Incidents!$H:$H,"Mineur") -> 0 | C12: =COUNTIFS(Incidents!$B:$B,">="&DATE(YEAR(Paramètres!$B$7),2,1),Incidents!$B:$B,"<"&EDATE(DATE(YEAR(Paramètres!$B$7),2,1),1),Incidents!$H:$H,"Mineur") -> 0 | D12: =COUNTIFS(Incidents!$B:$B,">="&DATE(YEAR(Paramètres!$B$7),3,1),Incidents!$B:$B,"<"&EDATE(DATE(YEAR(Paramètres!$B$7),3,1),1),Incidents!$H:$H,"Mineur") -> 0 | E12: =COUNTIFS(Incidents!$B:$B,">="&DATE(YEAR(Paramètres!$B$7),4,1),Incidents!$B:$B,"<"&EDATE(DATE(YEAR(Paramètres!$B$7),4,1),1),Incidents!$H:$H,"Mineur") -> 0 | F12: =COUNTIFS(Incidents!$B:$B,">="&DATE(YEAR(Paramètres!$B$7),5,1),Incidents!$B:$B,"<"&EDATE(DATE(YEAR(Paramètres!$B$7),5,1),1),Incidents!$H:$H,"Mineur") -> 0 | G12: =COUNTIFS(Incidents!$B:$B,">="&DATE(YEAR(Paramètres!$B$7),6,1),Incidents!$B:$B,"<"&EDATE(DATE(YEAR(Paramètres!$B$7),6,1),1),Incidents!$H:$H,"Mineur") -> 0 | H12: =COUNTIFS(Incidents!$B:$B,">="&DATE(YEAR(Paramètres!$B$7),7,1),Incidents!$B:$B,"<"&EDATE(DATE(YEAR(Paramètres!$B$7),7,1),1),Incidents!$H:$H,"Mineur") -> 0 | I12: =COUNTIFS(Incidents!$B:$B,">="&DATE(YEAR(Paramètres!$B$7),8,1),Incidents!$B:$B,"<"&EDATE(DATE(YEAR(Paramètres!$B$7),8,1),1),Incidents!$H:$H,"Mineur") -> 0 | J12: =COUNTIFS(Incidents!$B:$B,">="&DATE(YEAR(Paramètres!$B$7),9,1),Incidents!$B:$B,"<"&EDATE(DATE(YEAR(Paramètres!$B$7),9,1),1),Incidents!$H:$H,"Mineur") -> 0 | K12: =COUNTIFS(Incidents!$B:$B,">="&DATE(YEAR(Paramètres!$B$7),10,1),Incidents!$B:$B,"<"&EDATE(DATE(YEAR(Paramètres!$B$7),10,1),1),Incidents!$H:$H,"Mineur") -> 0 | L12: =COUNTIFS(Incidents!$B:$B,">="&DATE(YEAR(Paramètres!$B$7),11,1),Incidents!$B:$B,"<"&EDATE(DATE(YEAR(Paramètres!$B$7),11,1),1),Incidents!$H:$H,"Mineur") -> 0 | M12: =COUNTIFS(Incidents!$B:$B,">="&DATE(YEAR(Paramètres!$B$7),12,1),Incidents!$B:$B,"<"&EDATE(DATE(YEAR(Paramètres!$B$7),12,1),1),Incidents!$H:$H,"Mineur") -> 0 | N12: =SUM(B12:M12) -> 0
A13: Incidents significatifs | B13: =COUNTIFS(Incidents!$B:$B,">="&DATE(YEAR(Paramètres!$B$7),1,1),Incidents!$B:$B,"<"&EDATE(DATE(YEAR(Paramètres!$B$7),1,1),1),Incidents!$H:$H,"Significatif") -> 0 | C13: =COUNTIFS(Incidents!$B:$B,">="&DATE(YEAR(Paramètres!$B$7),2,1),Incidents!$B:$B,"<"&EDATE(DATE(YEAR(Paramètres!$B$7),2,1),1),Incidents!$H:$H,"Significatif") -> 0 | D13: =COUNTIFS(Incidents!$B:$B,">="&DATE(YEAR(Paramètres!$B$7),3,1),Incidents!$B:$B,"<"&EDATE(DATE(YEAR(Paramètres!$B$7),3,1),1),Incidents!$H:$H,"Significatif") -> 0 | E13: =COUNTIFS(Incidents!$B:$B,">="&DATE(YEAR(Paramètres!$B$7),4,1),Incidents!$B:$B,"<"&EDATE(DATE(YEAR(Paramètres!$B$7),4,1),1),Incidents!$H:$H,"Significatif") -> 0 | F13: =COUNTIFS(Incidents!$B:$B,">="&DATE(YEAR(Paramètres!$B$7),5,1),Incidents!$B:$B,"<"&EDATE(DATE(YEAR(Paramètres!$B$7),5,1),1),Incidents!$H:$H,"Significatif") -> 0 | G13: =COUNTIFS(Incidents!$B:$B,">="&DATE(YEAR(Paramètres!$B$7),6,1),Incidents!$B:$B,"<"&EDATE(DATE(YEAR(Paramètres!$B$7),6,1),1),Incidents!$H:$H,"Significatif") -> 0 | H13: =COUNTIFS(Incidents!$B:$B,">="&DATE(YEAR(Paramètres!$B$7),7,1),Incidents!$B:$B,"<"&EDATE(DATE(YEAR(Paramètres!$B$7),7,1),1),Incidents!$H:$H,"Significatif") -> 0 | I13: =COUNTIFS(Incidents!$B:$B,">="&DATE(YEAR(Paramètres!$B$7),8,1),Incidents!$B:$B,"<"&EDATE(DATE(YEAR(Paramètres!$B$7),8,1),1),Incidents!$H:$H,"Significatif") -> 0 | J13: =COUNTIFS(Incidents!$B:$B,">="&DATE(YEAR(Paramètres!$B$7),9,1),Incidents!$B:$B,"<"&EDATE(DATE(YEAR(Paramètres!$B$7),9,1),1),Incidents!$H:$H,"Significatif") -> 0 | K13: =COUNTIFS(Incidents!$B:$B,">="&DATE(YEAR(Paramètres!$B$7),10,1),Incidents!$B:$B,"<"&EDATE(DATE(YEAR(Paramètres!$B$7),10,1),1),Incidents!$H:$H,"Significatif") -> 0 | L13: =COUNTIFS(Incidents!$B:$B,">="&DATE(YEAR(Paramètres!$B$7),11,1),Incidents!$B:$B,"<"&EDATE(DATE(YEAR(Paramètres!$B$7),11,1),1),Incidents!$H:$H,"Significatif") -> 0 | M13: =COUNTIFS(Incidents!$B:$B,">="&DATE(YEAR(Paramètres!$B$7),12,1),Incidents!$B:$B,"<"&EDATE(DATE(YEAR(Paramètres!$B$7),12,1),1),Incidents!$H:$H,"Significatif") -> 0 | N13: =SUM(B13:M13) -> 0
A14: Incidents graves | B14: =COUNTIFS(Incidents!$B:$B,">="&DATE(YEAR(Paramètres!$B$7),1,1),Incidents!$B:$B,"<"&EDATE(DATE(YEAR(Paramètres!$B$7),1,1),1),Incidents!$H:$H,"Grave") -> 0 | C14: =COUNTIFS(Incidents!$B:$B,">="&DATE(YEAR(Paramètres!$B$7),2,1),Incidents!$B:$B,"<"&EDATE(DATE(YEAR(Paramètres!$B$7),2,1),1),Incidents!$H:$H,"Grave") -> 0 | D14: =COUNTIFS(Incidents!$B:$B,">="&DATE(YEAR(Paramètres!$B$7),3,1),Incidents!$B:$B,"<"&EDATE(DATE(YEAR(Paramètres!$B$7),3,1),1),Incidents!$H:$H,"Grave") -> 0 | E14: =COUNTIFS(Incidents!$B:$B,">="&DATE(YEAR(Paramètres!$B$7),4,1),Incidents!$B:$B,"<"&EDATE(DATE(YEAR(Paramètres!$B$7),4,1),1),Incidents!$H:$H,"Grave") -> 0 | F14: =COUNTIFS(Incidents!$B:$B,">="&DATE(YEAR(Paramètres!$B$7),5,1),Incidents!$B:$B,"<"&EDATE(DATE(YEAR(Paramètres!$B$7),5,1),1),Incidents!$H:$H,"Grave") -> 0 | G14: =COUNTIFS(Incidents!$B:$B,">="&DATE(YEAR(Paramètres!$B$7),6,1),Incidents!$B:$B,"<"&EDATE(DATE(YEAR(Paramètres!$B$7),6,1),1),Incidents!$H:$H,"Grave") -> 0 | H14: =COUNTIFS(Incidents!$B:$B,">="&DATE(YEAR(Paramètres!$B$7),7,1),Incidents!$B:$B,"<"&EDATE(DATE(YEAR(Paramètres!$B$7),7,1),1),Incidents!$H:$H,"Grave") -> 0 | I14: =COUNTIFS(Incidents!$B:$B,">="&DATE(YEAR(Paramètres!$B$7),8,1),Incidents!$B:$B,"<"&EDATE(DATE(YEAR(Paramètres!$B$7),8,1),1),Incidents!$H:$H,"Grave") -> 0 | J14: =COUNTIFS(Incidents!$B:$B,">="&DATE(YEAR(Paramètres!$B$7),9,1),Incidents!$B:$B,"<"&EDATE(DATE(YEAR(Paramètres!$B$7),9,1),1),Incidents!$H:$H,"Grave") -> 0 | K14: =COUNTIFS(Incidents!$B:$B,">="&DATE(YEAR(Paramètres!$B$7),10,1),Incidents!$B:$B,"<"&EDATE(DATE(YEAR(Paramètres!$B$7),10,1),1),Incidents!$H:$H,"Grave") -> 0 | L14: =COUNTIFS(Incidents!$B:$B,">="&DATE(YEAR(Paramètres!$B$7),11,1),Incidents!$B:$B,"<"&EDATE(DATE(YEAR(Paramètres!$B$7),11,1),1),Incidents!$H:$H,"Grave") -> 0 | M14: =COUNTIFS(Incidents!$B:$B,">="&DATE(YEAR(Paramètres!$B$7),12,1),Incidents!$B:$B,"<"&EDATE(DATE(YEAR(Paramètres!$B$7),12,1),1),Incidents!$H:$H,"Grave") -> 0 | N14: =SUM(B14:M14) -> 0
A15: Taux de satisfaction moyen | N15: =IFERROR(AVERAGE(B15:M15),"")
A16: Taux de ponctualité | N16: =IFERROR(AVERAGE(B16:M16),"")
A17: Échéance bancaire payée ? | N17: =COUNTIF(B17:M17,"Oui")&" / 12" -> 0 / 12
A20: Synthèse pour reporting bancaire
A22: KPI | B22: Valeur | C22: Seuil / Lecture | D22: Commentaire
A23: CA encaissé annuel | B23: =N7 -> 0 | C23: Suivi des recettes
A24: Solde net annuel | B24: =N9 -> 0 | C24: Recettes - sorties
A25: Réclamations ouvertes | B25: =COUNTIF(Réclamations!$M:$M,"<>Clôturée")-1 -> 1048575 | C25: À traiter sous 72h
A26: Incidents graves | B26: =N14 -> 0 | C26: Objectif : 0
